{
    "modules": [
        {
            "name": "core",
            "pip": "-e ./src/core"
        },
        {
            "name": "individual",
            "pip": "-e ./src/individual"
        },
        {
            "name": "workflow",
            "pip": "-e ./src/workflow"
        },
        {
            "name": "tasks_management",
            "pip": "-e ./src/tasks_management"
        },
        {
            "name": "report",
            "pip": "-e ./src/report"
        },
        {
            "name": "location",
            "pip": "-e ./src/location"
        },
        {
            "name": "medical",
            "pip": "-e ./src/medical"
        },
        {
            "name": "medical_pricelist",
            "pip": "-e ./src/medical_pricelist"
        },
        {
            "name": "product",
            "pip": "-e ./src/product"
        },
        {
            "name": "insuree",
            "pip": "-e ./src/insuree"
        },
        {
            "name": "policy",
            "pip": "-e ./src/policy"
        },
        {
            "name": "contribution",
            "pip": "-e ./src/contribution"
        },
        {
            "name": "payer",
            "pip": "-e ./src/payer"
        },
        {
            "name": "payment",
            "pip": "-e ./src/payment"
        },
        {
            "name": "claim",
            "pip": "-e ./src/claim"
        },
        {
            "name": "claim_batch",
            "pip": "-e ./src/claim_batch"
        },
        {
            "name": "tools",
            "pip": "-e ./src/tools"
        },
        {
            "name": "api_fhir_r4",
            "pip": "-e ./src/api_fhir_r4"
        },
        {
            "name": "calculation",
            "pip": "-e ./src/calculation"
        },
        {
            "name": "contribution_plan",
            "pip": "-e ./src/contribution_plan"
        },
        {
            "name": "policyholder",
            "pip": "-e ./src/policyholder"
        },
        {
            "name": "contract",
            "pip": "-e ./src/contract"
        },
        {
            "name": "invoice",
            "pip": "-e ./src/invoice"
        },
        {
            "name": "calcrule_contribution_legacy",
            "pip": "-e ./src/calcrule_contribution_legacy"
        },
        {
            "name": "calcrule_third_party_payment",
            "pip": "-e ./src/calcrule_third_party_payment"
        },
        {
            "name": "calcrule_capitation_payment",
            "pip": "-e ./src/calcrule_capitation_payment"
        },
        {
            "name": "calcrule_commission",
            "pip": "-e ./src/calcrule_commission"
        },
        {
            "name": "calcrule_contribution_income_percentage",
            "pip": "-e ./src/calcrule_contribution_income_percentage"
        },
        {
            "name": "calcrule_fees",
            "pip": "-e ./src/calcrule_fees"
        },
        {
            "name": "calcrule_unconditional_cash_payment",
            "pip": "-e ./src/calcrule_unconditional_cash_payment"
        },
        {
            "name": "im_export",
            "pip": "-e ./src/im_export"
        },
        {
            "name": "dhis2_etl",
            "pip": "-e ./src/dhis2_etl"
        },
        {
            "name": "social_protection",
            "pip": "-e ./src/social_protection"
        },
        {
            "name": "opensearch_reports",
            "pip": "-e ./src/opensearch_reports"
        },
        {
            "name": "payment_cycle",
            "pip": "-e ./src/payment_cycle"
        },
        {
            "name": "calcrule_social_protection",
            "pip": "-e ./src/calcrule_social_protection"
        },
        {
            "name": "payroll",
            "pip": "-e ./src/payroll"
        },
        {
            "name": "controls",
            "pip": "-e ./src/controls"
        },
        {
            "name": "grievance",
            "pip": "-e ./src/grievance"
        }
    ]
}
